structured_text/__init__.py
structured_text/_version.py
structured_text/handlers.py
structured_text/labextension/package.json
structured_text/labextension/schemas/structured_text/package.json.orig
structured_text/labextension/schemas/structured_text/plugin.json
structured_text/labextension/static/747.a8dd2290dd7cded4ff44.js
structured_text/labextension/static/763.5757d9821ddfffa6007e.js
structured_text/labextension/static/remoteEntry.8fde27dc2f51d153a148.js
structured_text/labextension/static/style.js
structured_text/labextension/static/third-party-licenses.json
structured_text-0.0.2.data/data/etc/jupyter/jupyter_notebook_config.d/structured_text.json
structured_text-0.0.2.data/data/etc/jupyter/jupyter_server_config.d/structured_text.json
structured_text-0.0.2.data/data/share/jupyter/labextensions/structured_text/install.json
structured_text-0.0.2.data/data/share/jupyter/labextensions/structured_text/package.json
structured_text-0.0.2.data/data/share/jupyter/labextensions/structured_text/schemas/structured_text/package.json.orig
structured_text-0.0.2.data/data/share/jupyter/labextensions/structured_text/schemas/structured_text/plugin.json
structured_text-0.0.2.data/data/share/jupyter/labextensions/structured_text/static/747.a8dd2290dd7cded4ff44.js
structured_text-0.0.2.data/data/share/jupyter/labextensions/structured_text/static/763.5757d9821ddfffa6007e.js
structured_text-0.0.2.data/data/share/jupyter/labextensions/structured_text/static/remoteEntry.8fde27dc2f51d153a148.js
structured_text-0.0.2.data/data/share/jupyter/labextensions/structured_text/static/style.js
structured_text-0.0.2.data/data/share/jupyter/labextensions/structured_text/static/third-party-licenses.json
structured_text-0.0.2.dist-info/LICENSE
structured_text-0.0.2.dist-info/METADATA
structured_text-0.0.2.dist-info/WHEEL
structured_text-0.0.2.dist-info/top_level.txt
structured_text-0.0.2.dist-info/RECORD
