Metadata-Version: 2.1
Name: structured-text
Version: 0.0.2
Summary: Interpret human-readable text and produce corresponding structured data.
Home-page: https://github.com/dyzfromyt/structured_text
Author: dyzfromyt@gmail.com
Author-email: dyzfromyt@gmail.com
License: BSD-3-Clause
Keywords: Jupyter,JupyterLab,JupyterLab3
Platform: Linux
Platform: Mac OS X
Platform: Windows
Classifier: Development Status :: 2 - Pre-Alpha
Classifier: Framework :: Jupyter
Classifier: Framework :: Jupyter :: JupyterLab
Classifier: Framework :: Jupyter :: JupyterLab :: 3
Classifier: Framework :: Jupyter :: JupyterLab :: Extensions
Classifier: Framework :: Jupyter :: JupyterLab :: Extensions :: Prebuilt
Classifier: License :: OSI Approved :: Apache Software License
Classifier: Programming Language :: Python
Classifier: Programming Language :: Python :: 3
Requires-Python: >=3.6
License-File: LICENSE
Requires-Dist: jupyter-server (<2,>=1.6)
